README.rst
demultipart.py
setup.py
demultipart.egg-info/PKG-INFO
demultipart.egg-info/SOURCES.txt
demultipart.egg-info/dependency_links.txt
demultipart.egg-info/entry_points.txt
demultipart.egg-info/top_level.txt
demultipart.egg-info/zip-safe