Metadata-Version: 1.1
Name: demultipart
Version: 0.2
Summary: Unpack a MIME message into a directory of files.
Home-page: http://github.com/vpelletier/demultipart
Author: Vincent Pelletier
Author-email: plr.vincent@gmail.com
License: GPL 2+
Platform: any
Classifier: License :: OSI Approved :: GNU General Public License v2 or later (GPLv2+)
Classifier: Operating System :: OS Independent
Classifier: Programming Language :: Python :: 2.7
Classifier: Programming Language :: Python :: 3
Classifier: Programming Language :: Python :: Implementation :: PyPy
Classifier: Programming Language :: Python :: Implementation :: CPython
